Metadata-Version: 2.1
Name: data-to-object
Version: 0.0.1
Summary: This is a simple package that deserializes json to your custom model include custom attributes and child objects.
Home-page: https://github.com/EnvInc/JsonToModel
Author: Original author: Denna Sun, Maintained by Vladimir Podolian
Author-email: vladimir.podlyan64@gmail.com
Classifier: Programming Language :: Python :: 3
Classifier: License :: OSI Approved :: MIT License
Classifier: Operating System :: OS Independent
Requires-Python: >=3.7
License-File: LICENSE
